patterns_components/__init__.py
patterns_components/components/__init__.py
patterns_components/components/utilities/__init__.py
patterns_components/components/utilities/generate_date_table/__init__.py
patterns_components/components/utilities/generate_date_table/base.py
patterns_components/components/utilities/generate_date_table/generate-date-table.yml
patterns_components/components/utilities/generate_date_table/generate_date_table.py
patterns_components/components/utilities/generate_date_table/readme.md
patterns_components/components/utilities/generate_date_table/schemas/DateTable.yml
patterns_components/components/utilities/generate_date_table/test_graph.yml
patterns_components/components/vendor/__init__.py
patterns_components/components/vendor/square/__init__.py
patterns_components/components/vendor/square/replication/__init__.py
patterns_components/components/vendor/square/replication/base.py
patterns_components/components/vendor/square/replication/importers.py
patterns_components/components/vendor/square/replication/locations.py
patterns_components/components/vendor/square/replication/readme.md
patterns_components/components/vendor/square/replication/replicate_all_tables.py
patterns_components/components/vendor/square/replication.yml
patterns_components/components/vendor/square/schemas/SquareCatalogObject.yml
patterns_components/components/vendor/square/schemas/SquareCustomer.yml
patterns_components/components/vendor/square/schemas/SquareLoyaltyAccount.yml
patterns_components/components/vendor/square/schemas/SquareOrder.yml
patterns_components/components/vendor/square/schemas/SquarePayment.yml
patterns_components/components/vendor/square/test_graph.yml
patterns_components/components/vendor/stripe/__init__.py
patterns_components/components/vendor/stripe/replication/__init__.py
patterns_components/components/vendor/stripe/replication/base.py
patterns_components/components/vendor/stripe/replication/readme.md
patterns_components-0.1.3.dist-info/LICENSE
patterns_components-0.1.3.dist-info/WHEEL
patterns_components-0.1.3.dist-info/METADATA
patterns_components-0.1.3.dist-info/RECORD
