Metadata-Version: 2.1
Name: patterns-components
Version: 0.1.3
Summary: Patterns open-source components
License: BSD-3-Clause
Requires-Python: >=3.8.1,<4.0.0
Classifier: License :: OSI Approved :: BSD License
Classifier: Programming Language :: Python :: 3
Classifier: Programming Language :: Python :: 3.9
Classifier: Programming Language :: Python :: 3.10
Classifier: Programming Language :: Python :: 3.11
Requires-Dist: pandas (>=1.4.2,<2.0.0)
Requires-Dist: patterns-devkit (>=1.4.0,<2.0.0)
Requires-Dist: python-dateutil (>=2.8.0,<3.0.0)
